ecko_cli/__init__.py
ecko_cli/__main__.py
ecko_cli/__version__.py
ecko_cli/analyze.py
ecko_cli/cli.py
ecko_cli/helpers.py
ecko_cli/images.py
ecko_cli/models/anime.csv
ecko_cli/models/realistic.csv
ecko_cli-1.6.0.dist-info/METADATA
ecko_cli-1.6.0.dist-info/WHEEL
ecko_cli-1.6.0.dist-info/entry_points.txt
ecko_cli-1.6.0.dist-info/licenses/LICENSE
ecko_cli-1.6.0.dist-info/RECORD
