Metadata-Version: 2.3
Name: ecko_cli
Version: 1.6.0
Summary: CLI tool that easily converts a directory of images into a dataset for training generative ai models
Project-URL: Repository, https://github.com/regiellis/ecko-cli
Project-URL: Documentation, https://github.com/regiellis/ecko-cli/blob/main/README.md
Project-URL: Bug Tracker, https://github.com/regiellis/ecko-cli/issues
Author-email: Regi E <regi@bynine.io>
License: Copyright 2024 Regi E Ellis
Keywords: ai,cli,dataset,florence-2,generative-ai,huggingface,image,image-classificatioon,image-processing,onnx,timm,torch,torchvision,training,transformers
Classifier: License :: OSI Approved :: Apache Software License
Classifier: Operating System :: OS Independent
Classifier: Programming Language :: Python :: 3.11
Requires-Python: >=3.11
Requires-Dist: einops
Requires-Dist: gradio
Requires-Dist: huggingface-hub[cli]
Requires-Dist: opencv-python
Requires-Dist: pillow
Requires-Dist: python-dotenv
Requires-Dist: rich
Requires-Dist: shellingham
Requires-Dist: timm
Requires-Dist: torch
Requires-Dist: torchvision
Requires-Dist: transformers
Requires-Dist: typer
